Workbook

Sheet Costos Indirectos
B1: Costos
B2: Descripción | C2: Anual | D2: Mensual | E2: Costo/empleado | H2: Empleados de la oficina | I2: 16
B4: Renta | C4: 250000 | D4: =+C4/12 -> 20833.333 | E4: =+D4/$I$2 -> 1302.0833
B5: Luz | C5: 36000 | D5: =+C5/12 -> 3000 | E5: =+D5/$I$2 -> 187.5
B6: Agua | C6: 12000 | D6: =+C6/12 -> 1000 | E6: =+D6/$I$2 -> 62.5
B7: Limpieza | C7: 55000 | D7: =+C7/12 -> 4583.3333 | E7: =+D7/$I$2 -> 286.45833
B8: Papelería | C8: 18000 | D8: =+C8/12 -> 1500 | E8: =+D8/$I$2 -> 93.75
B9: Varios | C9: 24000 | D9: =+C9/12 -> 2000 | E9: =+D9/$I$2 -> 125
B10: Caja | C10: 12000 | D10: =+C10/12 -> 1000 | E10: =+D10/$I$2 -> 62.5
B19: Total | C19: =SUM(C4:C18) -> 407000 | D19: =SUM(D4:D18) -> 33916.667 | E19: =+D19/$I$2 -> 2119.7917
B21: Estos importes son los de la plantilla original; se conservan como referencia y se deben validar.

Sheet Hw&SW
B1: Infraestructura
B2: Descripción | C2: Número | D2: Costo Unitario (MXN) | E2: Costo por proyecto (MXN) | F2: Base del cálculo | G2: Costo unitario (USD) | I2: Número de meses de duración | J2: =Notas!B4 -> 15
B3: Generadores de código de barras para salones | C3: 500 | D3: =+G3*Notas!$B$3 -> 22200 | E3: =+C3*D3 -> 11100000 | F3: Cantidad × costo unitario (compra) | G3: 1200 | I3: Empleados proyecto (máx.) | J3: =Notas!B5 -> 7
B4: Instalación, energía y conectividad en salones | C4: 500 | D4: =+G4*Notas!$B$3 -> 2775 | E4: =+C4*D4 -> 1387500 | F4: Cantidad × costo unitario (servicio) | G4: 150
B5: Equipos administrativos con Windows 11 Pro | C5: 50 | D5: =+G5*Notas!$B$3 -> 18500 | E5: =+C5*D5 -> 925000 | F5: Cantidad × costo unitario (compra) | G5: 1000
B6: Microsoft 365 Business Premium (primer año) | C6: 50 | D6: =+G6*Notas!$B$3 -> 4884 | E6: =+C6*D6 -> 244200 | F6: Cantidad × costo del primer año completo | G6: 264
B7: Infraestructura en la nube durante el proyecto | C7: 1 | D7: =+G7*Notas!$B$3 -> 55500 | E7: =+C7*D7*$J$2 -> 832500 | F7: Cantidad × costo mensual × meses | G7: 3000
B8: Herramientas y licencias de desarrollo (IDE, Enterprise Architect, tiendas móviles) | C8: =J3 -> 7 | D8: =+G8*Notas!$B$3 -> 18500 | E8: =+C8*D8 -> 129500 | F8: Licencias para el equipo máximo × costo unitario | G8: 1000
B9: Servicios de terceros (pasarela de pago, SMS y correo, certificados) | C9: 1 | D9: =+G9*Notas!$B$3 -> 185000 | E9: =+C9*D9 -> 185000 | F9: Costo del proyecto | G9: 10000
B16: Totales | E16: =SUM(E3:E15) -> 14803700 | G16: =+E16/Notas!$B$3 -> 800200
B18: Las cifras en dólares coinciden con el Documento 2, sección 3.3 (factibilidad económica).

Sheet Sueldos
B2: Sueldos
B3: Puesto | C3: Mensual (MXN) | D3: Recursos Proyecto (máx.) | E3: Total Mensual | F3: Total Proyecto | G3: Tiempo a Utilizar (meses eq.) | H3: Persona-mes | I3: Actividad COCOMO II (RUP/MBASE)
B4: Director de proyecto | C4: =Notas!$B$7*Notas!$B$8 -> 32000 | D4: 1 | E4: =+D4*C4 -> 32000 | F4: =+E4*G4 -> 169600 | G4: 5.3 | H4: =+D4*G4 -> 5.3 | I4: Management: 0.3 + 1.2 + 3.1 + 0.7
B5: Analista de requisitos | C5: =Notas!$B$7*Notas!$B$8 -> 32000 | D5: 1 | E5: =+D5*C5 -> 32000 | F5: =+E5*G5 -> 172800 | G5: 5.4 | H5: =+D5*G5 -> 5.4 | I5: Requirements: 0.9 + 1.8 + 2.5 + 0.2
B6: Arquitecto y diseñador de software | C6: =Notas!$B$7*Notas!$B$8 -> 32000 | D6: 1 | E6: =+D6*C6 -> 32000 | F6: =+E6*G6 -> 291200 | G6: 9.1 | H6: =+D6*G6 -> 9.1 | I6: Design: 0.5 + 3.5 + 4.9 + 0.2
B7: Desarrollador .NET (web, API y móvil) | C7: =Notas!$B$7*Notas!$B$8 -> 32000 | D7: 2 | E7: =+D7*C7 -> 64000 | F7: =+E7*G7 -> 412800 | G7: 6.45 | H7: =+D7*G7 -> 12.9 | I7: Implementation: 0.2 + 1.3 + 10.5 + 0.9 = 12.9
B8: Ingeniero de pruebas (QA) | C8: =Notas!$B$7*Notas!$B$8 -> 32000 | D8: 1 | E8: =+D8*C8 -> 32000 | F8: =+E8*G8 -> 313600 | G8: 9.8 | H8: =+D8*G8 -> 9.8 | I8: Assessment: 0.2 + 1.0 + 7.4 + 1.2
B9: Ingeniero DevOps (ambiente, configuración y despliegue) | C9: =Notas!$B$7*Notas!$B$8 -> 32000 | D9: 1 | E9: =+D9*C9 -> 32000 | F9: =+E9*G9 -> 176000 | G9: 5.5 | H9: =+D9*G9 -> 5.5 | I9: Environment/CM 2.7 + Deployment 2.8
B18: Totales | D18: =SUM(D4:D17) -> 7 | E18: =SUM(E4:E17) -> 224000 | F18: =SUM(F4:F17) -> 1536000 | H18: =SUM(H4:H17) -> 48
B20: Los persona-mes de la columna H suman 48.0, la distribución por actividad de COCOMO II del Documento 1 (hoja COCOMO_Doc1).

Sheet Otros
B2: Otros Costos
B3: Descripción | C3: Nùmero | D3: Costo (MXN) | E3: Total (MXN) | F3: Costo (USD)
B4: Auditoría de seguridad y pruebas de penetración | C4: 1 | D4: =+F4*Notas!$B$3 -> 370000 | E4: =+D4*C4 -> 370000 | F4: 20000
B5: Gestión del cambio y comunicación interna | C5: 1 | D5: =+F5*Notas!$B$3 -> 185000 | E5: =+D5*C5 -> 185000 | F5: 10000
B10: Totales | E10: =SUM(E4:E9) -> 555000 | F10: =+E10/Notas!$B$3 -> 30000
B12: No se presupuestan viajes: el proyecto se ejecuta en la Ciudad de México y la integración con el corporativo de España es por web service.

Sheet TotalProyecto
B2: Resumen Costos
B3: Descripciòn | C3: Costo (MXN) | D3: Costo (USD) | E3: Origen
B4: Indirectos | C4: =+'Costos Indirectos'!E19*Sueldos!H18 -> 101750 | D4: =+C4/Notas!$B$3 -> 5500 | E4: Costo indirecto por empleado al mes × 48.0 persona-mes (COCOMO II)
B5: Infraestructura | C5: =+'Hw&SW'!E16 -> 14803700 | D5: =+C5/Notas!$B$3 -> 800200 | E5: Hoja Hw&SW (Documento 2, sección 3.3)
B6: Sueldos | C6: =+Sueldos!F18 -> 1536000 | D6: =+C6/Notas!$B$3 -> 83027.027 | E6: Hoja Sueldos: 48.0 persona-mes (COCOMO II) × 32,000 MXN
B7: Otros | C7: =+Otros!E10 -> 555000 | D7: =+C7/Notas!$B$3 -> 30000 | E7: Hoja Otros (Documento 2, sección 3.3)
B8: Costos directos del proyecto | C8: =SUM(C4:C7) -> 16996450 | D8: =+C8/Notas!$B$3 -> 918727.03 | E8: Suma de los cuatro rubros anteriores
B9: Reserva de contingencia (10%) | C9: =+C8*0.1 -> 1699645 | D9: =+C9/Notas!$B$3 -> 91872.703 | E9: Documento 2, sección 3.3
B10: Línea base de costos | C10: =+C8+C9 -> 18696095 | D10: =+C10/Notas!$B$3 -> 1010599.7 | E10: Costos directos más la reserva de contingencia
B11: Reserva de gestión | C11: =+C12-C10 -> 18303905 | D11: =+C11/Notas!$B$3 -> 989400.27 | E11: Lo que resta del presupuesto autorizado; queda bajo control del patrocinador
B12: Presupuesto autorizado | C12: =2000000*Notas!$B$3 -> 37000000 | D12: =+C12/Notas!$B$3 -> 2000000 | E12: Enunciado de la Práctica 2: 2 millones de USD
B13: Margen de la línea base contra el presupuesto | C13: =IF(C10<=C12,"Dentro del presupuesto","Excede el presupuesto") -> Dentro del presupuesto | D13: =IF(C10<=C12,"Margen: "&TEXT((C12-C10)/Notas!$B$3,"$#,##0")&" USD","") -> Margen: $989,400 USD | E13: La línea base debe caber en el presupuesto autorizado
B15: Las cifras de este resumen coinciden con el Documento 2, sección 3.3: costos directos, reservas y presupuesto autorizado, incluidos los costos indirectos.
B17: Esfuerzo COCOMO II (persona-mes) | C17: =Sueldos!H18 -> 48
B18: Duración del proyecto (meses) | C18: =Notas!B4 -> 15

Sheet Notas
A1: Costos del proyecto – Academia de idiomas (Equipo 7)
A2: Parámetros del cálculo (celdas que se pueden ajustar)
A3: Tipo de cambio (MXN por USD) | B3: 18.5 | C3: Tipo de cambio de referencia usado en el Documento 2.
A4: Duración del proyecto (meses) | B4: 15 | C4: Documento 1, gráfica de Gantt: Inicio 1.5, Elaboración 4.5, Construcción 7.4 y Transición 1.5 meses (≈ 15 meses).
A5: Equipo máximo del proyecto (personas) | B5: =Sueldos!D18 -> 7 | C5: Personas simultáneas en la hoja Sueldos. El promedio es 48.0 persona-mes / 15 meses = 3.2 personas.
A6: Esfuerzo total (persona-mes) | B6: =Sueldos!H18 -> 48 | C6: COCOMO II de diseño temprano (Documento 1): 40.6 PM en Elaboración y Construcción; 47.9 PM con Inicio y Transición; la distribución por actividad suma 48.0 PM.
A7: Sueldo por hora (MXN) | B7: 200 | C7: Enunciado de la Práctica 2: sueldo promedio de 200 pesos la hora.
A8: Horas por mes | B8: 160 | C8: Base mensual usada en el Documento 2 (160 h/mes).
A10: Notas del Equipo 7
A11: 1. Las cifras del Documento 2 están en dólares; en este libro se convierten a pesos con el tipo de cambio de la celda B3, porque la plantilla y el sueldo de la práctica están en pesos.
A12: 2. Sueldos: la práctica fija un sueldo promedio de 200 pesos por hora, así que todos los puestos usan 32,000 MXN al mes (200 × 160 h), el mismo costo por persona-mes que se capturó en la herramienta COCOMO II.
A13: 3. En la hoja Sueldos, los persona-mes de cada puesto salen de la distribución por actividad RUP/MBASE de COCOMO II (hoja COCOMO_Doc1). Recursos es el número máximo de personas simultáneas y Tiempo a Utilizar son los meses equivalentes de tiempo completo.
A14: 4. Correcciones a las fórmulas de la plantilla: en Hw&SW cada renglón multiplica cantidad por costo y, cuando el gasto es recurrente, por los meses. En TotalProyecto el total suma C4:C7 (incluye Otros).
A15: 5. Los costos indirectos (renta, luz, agua, limpieza, papelería, varios y caja) son valores de referencia de la plantilla y deben validarse. Se cargan por persona-mes (costo por empleado al mes × 48.0 PM) porque el equipo no trabaja tiempo completo los 15 meses.
A16: 6. La reserva de contingencia (10%) y la reserva de gestión coinciden con el Documento 2, sección 3.3.
A17: 7. La distribución por actividad de COCOMO II suma 48.0 PM y la de fases 47.9 PM (costo de la herramienta: $1,532,357 MXN). El presupuesto usa 48.0 PM: $3,643 MXN más (0.2%), por redondeo del reporte.

Sheet COCOMO_Doc1
A1: COCOMO II de diseño temprano – resultados del Documento 1 (P2_JD)
A2: 136 PF sin ajustar, lenguaje de 3ª generación (10,880 SLOC), factores de escala y de costo nominales, EAF = 1.00, 32,000 MXN por persona-mes.
A4: Escenario | B4: Persona-mes | C4: Costo de personal | D4: Indirectos | E4: Línea base | F4: Margen vs. $2 MDD
A5: Inicio | B5: 2.4 | C5: 1.5 | D5: 1.6 | E5: 77916 | F5: =B5*Notas!$B$7*Notas!$B$8 -> 76800
A6: Elaboración | B6: 9.7 | C6: 4.5 | D6: 2.2 | E6: 311666 | F6: =B6*Notas!$B$7*Notas!$B$8 -> 310400
A7: Construcción | B7: 30.8 | C7: 7.4 | D7: 4.1 | E7: 986942 | F7: =B7*Notas!$B$7*Notas!$B$8 -> 985600
A8: Transición | B8: 4.9 | C8: 1.5 | D8: 3.3 | E8: 155833 | F8: =B8*Notas!$B$7*Notas!$B$8 -> 156800
A9: Total | B9: =SUM(B5:B8) -> 47.8 | C9: =SUM(C5:C8) -> 14.9 | E9: =SUM(E5:E8) -> 1532357 | F9: =SUM(F5:F8) -> 1529600
A10: Elaboración + Construcción (lo que reporta COCOMO II como Effort y Schedule) | B10: =B6+B7 -> 40.5 | C10: =C6+C7 -> 11.9 | D10: La herramienta reporta 40.6 PM por redondeo de las fases.
A12: Actividad | B12: Inicio | C12: Elaboración | D12: Construcción | E12: Transición | F12: Total (PM) | G12: Puesto en la hoja Sueldos
A13: Management | B13: 0.3 | C13: 1.2 | D13: 3.1 | E13: 0.7 | F13: =SUM(B13:E13) -> 5.3 | G13: Director de proyecto
A14: Environment/CM | B14: 0.2 | C14: 0.8 | D14: 1.5 | E14: 0.2 | F14: =SUM(B14:E14) -> 2.7 | G14: Ingeniero DevOps
A15: Requirements | B15: 0.9 | C15: 1.8 | D15: 2.5 | E15: 0.2 | F15: =SUM(B15:E15) -> 5.4 | G15: Analista de requisitos
A16: Design | B16: 0.5 | C16: 3.5 | D16: 4.9 | E16: 0.2 | F16: =SUM(B16:E16) -> 9.1 | G16: Arquitecto y diseñador
A17: Implementation | B17: 0.2 | C17: 1.3 | D17: 10.5 | E17: 0.9 | F17: =SUM(B17:E17) -> 12.9 | G17: Desarrolladores .NET (2)
A18: Assessment | B18: 0.2 | C18: 1 | D18: 7.4 | E18: 1.2 | F18: =SUM(B18:E18) -> 9.8 | G18: Ingeniero de pruebas (QA)
A19: Deployment | B19: 0.1 | C19: 0.3 | D19: 0.9 | E19: 1.5 | F19: =SUM(B19:E19) -> 2.8 | G19: Ingeniero DevOps
A20: Total | B20: =SUM(B13:B19) -> 2.4 | C20: =SUM(C13:C19) -> 9.9 | D20: =SUM(D13:D19) -> 30.8 | E20: =SUM(E13:E19) -> 4.9 | F20: =SUM(F13:F19) -> 48 | G20: =IF(ROUND(F20,1)=ROUND(Sueldos!H18,1),"Cuadra con Sueldos","Revisar Sueldos") -> Cuadra con Sueldos
A22: Compresión máxima del calendario (SCED muy bajo = 75%, multiplicador 1.43)
A23: Duración comprimida (meses) | B23: =C9*0.75 -> 11.175
A24: Esfuerzo con compresión (PM) | B24: =Sueldos!H18*1.43 -> 68.64
A25: Aun con la compresión máxima del modelo, la duración queda por encima de los 10 meses del enunciado.

Sheet Sensibilidad
A1: Análisis de sensibilidad (USD) – Documento 2, sección 3.3
A2: Las demás partidas se mantienen constantes; los indirectos se ajustan a los persona-mes de cada escenario.
A5: Base: COCOMO II (48.0 PM, $200 MXN/h) | B5: =Sueldos!H18 -> 48 | C5: =B5*Notas!$B$7*Notas!$B$8/Notas!$B$3 -> 83027.027 | D5: ='Costos Indirectos'!$E$19*B5/Notas!$B$3 -> 5500 | E5: =(C5+D5+('Hw&SW'!$E$16+Otros!$E$10)/Notas!$B$3)*1.1 -> 1010599.7 | F5: =2000000-E5 -> 989400.27
A6: Esfuerzo +30% | B6: =Sueldos!H18*1.3 -> 62.4 | C6: =B6*Notas!$B$7*Notas!$B$8/Notas!$B$3 -> 107935.14 | D6: ='Costos Indirectos'!$E$19*B6/Notas!$B$3 -> 7150 | E6: =(C6+D6+('Hw&SW'!$E$16+Otros!$E$10)/Notas!$B$3)*1.1 -> 1039813.6 | F6: =2000000-E6 -> 960186.35
A7: Calendario comprimido al 75% (SCED 1.43) | B7: =Sueldos!H18*1.43 -> 68.64 | C7: =B7*Notas!$B$7*Notas!$B$8/Notas!$B$3 -> 118728.65 | D7: ='Costos Indirectos'!$E$19*B7/Notas!$B$3 -> 7865 | E7: =(C7+D7+('Hw&SW'!$E$16+Otros!$E$10)/Notas!$B$3)*1.1 -> 1052473 | F7: =2000000-E7 -> 947526.99
A8: Tarifa de mercado ($35 USD/h) | B8: =Sueldos!H18 -> 48 | C8: =B8*Notas!$B$8*35 -> 268800 | D8: ='Costos Indirectos'!$E$19*B8/Notas!$B$3 -> 5500 | E8: =(C8+D8+('Hw&SW'!$E$16+Otros!$E$10)/Notas!$B$3)*1.1 -> 1214950 | F8: =2000000-E8 -> 785050
