Workbook

Sheet Costos Indirectos
B1: Costos
B2: Descripción | C2: Anual | D2: Mensual | E2: Costo/empleado | H2: Empleados (equipo del proyecto) | I2: ='Hw&SW'!J3 -> 7
B4: Renta | C4: 250000 | D4: =+C4/12 -> 20833.333 | E4: =+D4/$I$2 -> 2976.1905
B5: Luz | C5: 36000 | D5: =+C5/12 -> 3000 | E5: =+D5/$I$2 -> 428.57143
B6: Agua | C6: 12000 | D6: =+C6/12 -> 1000 | E6: =+D6/$I$2 -> 142.85714
B7: Limpieza | C7: 55000 | D7: =+C7/12 -> 4583.3333 | E7: =+D7/$I$2 -> 654.7619
B8: Papelería | C8: 18000 | D8: =+C8/12 -> 1500 | E8: =+D8/$I$2 -> 214.28571
B9: Varios | C9: 24000 | D9: =+C9/12 -> 2000 | E9: =+D9/$I$2 -> 285.71429
B10: Caja | C10: 12000 | D10: =+C10/12 -> 1000 | E10: =+D10/$I$2 -> 142.85714
B19: Total | C19: =SUM(C4:C18) -> 407000 | D19: =SUM(D4:D18) -> 33916.667 | E19: =+D19/$I$2 -> 4845.2381

Sheet Hw&SW
B1: Infraestructura
B2: Descripción | C2: Número | D2: Costo Unitario (MXN) | E2: Costo por proyecto (MXN) | F2: Base del cálculo | G2: Costo unitario (USD) | I2: Número de meses de duración | J2: =Notas!B4 -> 15
B3: Generadores de código de barras para salones | C3: 500 | D3: =+G3*Notas!$B$3 -> 22200 | E3: =+C3*D3 -> 11100000 | F3: Cantidad × costo unitario (compra) | G3: 1200 | I3: Empleados proyecto (máx.) | J3: =Notas!B5 -> 7
B4: Instalación, energía y conectividad en salones | C4: 500 | D4: =+G4*Notas!$B$3 -> 2775 | E4: =+C4*D4 -> 1387500 | F4: Cantidad × costo unitario (servicio) | G4: 150
B5: Equipos administrativos con Windows 11 Pro | C5: 50 | D5: =+G5*Notas!$B$3 -> 18500 | E5: =+C5*D5 -> 925000 | F5: Cantidad × costo unitario (compra) | G5: 1000
B6: Microsoft 365 Business Premium (primer año) | C6: 50 | D6: =+G6*Notas!$B$3 -> 4884 | E6: =+C6*D6 -> 244200 | F6: Cantidad × costo del primer año completo | G6: 264
B7: Infraestructura en la nube durante el proyecto | C7: 1 | D7: =+G7*Notas!$B$3 -> 55500 | E7: =+C7*D7*$J$2 -> 832500 | F7: Cantidad × costo mensual × meses | G7: 3000
B8: Herramientas y licencias de desarrollo (IDE, Enterprise Architect, tiendas móviles) | C8: =J3 -> 7 | D8: =+G8*Notas!$B$3 -> 18500 | E8: =+C8*D8 -> 129500 | F8: Licencias para el equipo máximo × costo unitario | G8: 1000
B9: Servicios de terceros (pasarela de pago, SMS y correo, certificados) | C9: 1 | D9: =+G9*Notas!$B$3 -> 185000 | E9: =+C9*D9 -> 185000 | F9: Costo del proyecto | G9: 10000
B10: Apple MacBook Pro 13" (compilación iOS de la app .NET MAUI) | C10: 1 | D10: 39000 | E10: =+C10*D10 -> 39000 | F10: Cantidad × costo unitario (compra; precio P1) | G10: =+D10/Notas!$B$3 -> 2108.1081
B11: Laptop Dell Inspiron 5584 Core i5, 8 GB (arquitecto, desarrollador y DevOps) | C11: 3 | D11: 22000 | E11: =+C11*D11 -> 66000 | F11: Cantidad × costo unitario (compra; precio P1) | G11: =+D11/Notas!$B$3 -> 1189.1892
B12: Laptop HP Pavilion (director, analista y QA) | C12: 3 | D12: 18000 | E12: =+C12*D12 -> 54000 | F12: Cantidad × costo unitario (compra; precio P1) | G12: =+D12/Notas!$B$3 -> 972.97297
B13: Office 365 para el equipo del proyecto | C13: =+$J$3 -> 7 | D13: 980 | E13: =+C13*D13 -> 6860 | F13: Licencias para el equipo máximo × costo (precio P1) | G13: =+D13/Notas!$B$3 -> 52.972973
B16: Totales | E16: =SUM(E3:E15) -> 14969560 | G16: =+E16/Notas!$B$3 -> 809165.41

Sheet Sueldos
B2: Sueldos
B3: Puesto | C3: Mensual ajustado (MXN) | D3: Recursos Proyecto (máx.) | E3: Total Mensual | F3: Total Proyecto | G3: Tiempo a Utilizar (meses eq.) | H3: Persona-mes | I3: Actividad COCOMO II (RUP/MBASE) | J3: Sueldo base P1 (MXN/mes) | K3: Puesto equivalente en la P1
B4: Director de proyecto | C4: =J4*Notas!$B$27 -> 35623.023 | D4: 1 | E4: =+D4*C4 -> 35623.023 | F4: =+E4*G4 -> 188802.02 | G4: 5.3 | H4: =+D4*G4 -> 5.3 | I4: Management: 0.3 + 1.2 + 3.1 + 0.7 | J4: 33000 | K4: Dirección Proyecto
B5: Analista de requisitos | C5: =J5*Notas!$B$27 -> 26987.139 | D5: 1 | E5: =+D5*C5 -> 26987.139 | F5: =+E5*G5 -> 145730.55 | G5: 5.4 | H5: =+D5*G5 -> 5.4 | I5: Requirements: 0.9 + 1.8 + 2.5 + 0.2 | J5: 25000 | K5: Analista
B6: Arquitecto y diseñador de software | C6: =J6*Notas!$B$27 -> 37781.995 | D6: 1 | E6: =+D6*C6 -> 37781.995 | F6: =+E6*G6 -> 343816.15 | G6: 9.1 | H6: =+D6*G6 -> 9.1 | I6: Design: 0.5 + 3.5 + 4.9 + 0.2 | J6: 35000 | K6: Arquitecto SW
B7: Desarrollador .NET (web, API y móvil) | C7: =J7*Notas!$B$27 -> 43179.422 | D7: 2 | E7: =+D7*C7 -> 86358.845 | F7: =+E7*G7 -> 557014.55 | G7: 6.45 | H7: =+D7*G7 -> 12.9 | I7: Implementation: 0.2 + 1.3 + 10.5 + 0.9 = 12.9 | J7: 40000 | K7: Programador
B8: Ingeniero de pruebas (QA) | C8: =J8*Notas!$B$27 -> 21589.711 | D8: 1 | E8: =+D8*C8 -> 21589.711 | F8: =+E8*G8 -> 211579.17 | G8: 9.8 | H8: =+D8*G8 -> 9.8 | I8: Assessment: 0.2 + 1.0 + 7.4 + 1.2 | J8: 20000 | K8: Tester
B9: Ingeniero DevOps (ambiente, configuración y despliegue) | C9: =J9*Notas!$B$27 -> 16192.283 | D9: 1 | E9: =+D9*C9 -> 16192.283 | F9: =+E9*G9 -> 89057.559 | G9: 5.5 | H9: =+D9*G9 -> 5.5 | I9: Environment/CM 2.7 + Deployment 2.8 | J9: 15000 | K9: Implementador
B18: Totales | D18: =SUM(D4:D17) -> 7 | E18: =SUM(E4:E17) -> 224533 | F18: =SUM(F4:F17) -> 1536000 | H18: =SUM(H4:H17) -> 48
B20: Los persona-mes de la columna H suman 48.0, la distribución por actividad de COCOMO II del Documento 1 (hoja COCOMO_Doc1).
B21: Columna C: sueldo base de la Práctica 1 × factor de ajuste (Notas B27), para que el promedio ponderado por persona-mes sea de 32,000 MXN (200 MXN/h).
B22: =IF(ROUND(F18/H18-Notas!B7*Notas!B8,2)=0,"Promedio por persona-mes = 32,000 MXN (200 MXN/h)","Revisar") -> Promedio por persona-mes = 32,000 MXN (200 MXN/h)

Sheet DesgloseIntegrantes
A1: Desglose de costos por integrante del equipo del proyecto
A2: Valores base del libro: sueldo por puesto (Sueldos), costo indirecto por empleado al mes (Costos Indirectos), equipo de cómputo, Office 365 y licencias de herramientas (Hw&SW) y meses de cada puesto (Sueldos).
A4: # | B4: Integrante | C4: Puesto | D4: Meses equivalentes | E4: Sueldo mensual (MXN) | F4: Sueldo total (MXN) | G4: Indirectos (MXN) | H4: Licencia de herramientas (MXN) | I4: Equipo de cómputo asignado | J4: Costo del equipo de cómputo (MXN) | K4: Office 365 (MXN) | L4: Total por integrante (MXN) | M4: Total (USD) | N4: % del total
A5: 1 | B5: Integrante 1 | C5: =Sueldos!B4 -> Director de proyecto | D5: =Sueldos!G4 -> 5.3 | E5: =Sueldos!C4 -> 35623.023 | F5: =D5*E5 -> 188802.02 | G5: ='Costos Indirectos'!$E$19*Notas!$B$4 -> 72678.571 | H5: ='Hw&SW'!$D$8 -> 18500 | I5: HP Pavilion | J5: ='Hw&SW'!$D$12 -> 18000 | K5: ='Hw&SW'!$D$13 -> 980 | L5: =F5+G5+H5+J5+K5 -> 298960.6 | M5: =L5/Notas!$B$3 -> 16160.032 | N5: =L5/$L$12 -> 0.12775493
A6: 2 | B6: Integrante 2 | C6: =Sueldos!B5 -> Analista de requisitos | D6: =Sueldos!G5 -> 5.4 | E6: =Sueldos!C5 -> 26987.139 | F6: =D6*E6 -> 145730.55 | G6: ='Costos Indirectos'!$E$19*Notas!$B$4 -> 72678.571 | H6: ='Hw&SW'!$D$8 -> 18500 | I6: HP Pavilion | J6: ='Hw&SW'!$D$12 -> 18000 | K6: ='Hw&SW'!$D$13 -> 980 | L6: =F6+G6+H6+J6+K6 -> 255889.12 | M6: =L6/Notas!$B$3 -> 13831.844 | N6: =L6/$L$12 -> 0.10934919
A7: 3 | B7: Integrante 3 | C7: =Sueldos!B6 -> Arquitecto y diseñador de software | D7: =Sueldos!G6 -> 9.1 | E7: =Sueldos!C6 -> 37781.995 | F7: =D7*E7 -> 343816.15 | G7: ='Costos Indirectos'!$E$19*Notas!$B$4 -> 72678.571 | H7: ='Hw&SW'!$D$8 -> 18500 | I7: Dell Inspiron | J7: ='Hw&SW'!$D$11 -> 22000 | K7: ='Hw&SW'!$D$13 -> 980 | L7: =F7+G7+H7+J7+K7 -> 457974.72 | M7: =L7/Notas!$B$3 -> 24755.39 | N7: =L7/$L$12 -> 0.19570649
A8: 4 | B8: Integrante 4 | C8: =Sueldos!B7 -> Desarrollador .NET (web, API y móvil) | D8: =Sueldos!G7 -> 6.45 | E8: =Sueldos!C7 -> 43179.422 | F8: =D8*E8 -> 278507.27 | G8: ='Costos Indirectos'!$E$19*Notas!$B$4 -> 72678.571 | H8: ='Hw&SW'!$D$8 -> 18500 | I8: Dell Inspiron | J8: ='Hw&SW'!$D$11 -> 22000 | K8: ='Hw&SW'!$D$13 -> 980 | L8: =F8+G8+H8+J8+K8 -> 392665.85 | M8: =L8/Notas!$B$3 -> 21225.181 | N8: =L8/$L$12 -> 0.16779803
A9: 5 | B9: Integrante 5 | C9: =Sueldos!B7 -> Desarrollador .NET (web, API y móvil) | D9: =Sueldos!G7 -> 6.45 | E9: =Sueldos!C7 -> 43179.422 | F9: =D9*E9 -> 278507.27 | G9: ='Costos Indirectos'!$E$19*Notas!$B$4 -> 72678.571 | H9: ='Hw&SW'!$D$8 -> 18500 | I9: MacBook Pro | J9: ='Hw&SW'!$D$10 -> 39000 | K9: ='Hw&SW'!$D$13 -> 980 | L9: =F9+G9+H9+J9+K9 -> 409665.85 | M9: =L9/Notas!$B$3 -> 22144.1 | N9: =L9/$L$12 -> 0.17506264
A10: 6 | B10: Integrante 6 | C10: =Sueldos!B8 -> Ingeniero de pruebas (QA) | D10: =Sueldos!G8 -> 9.8 | E10: =Sueldos!C8 -> 21589.711 | F10: =D10*E10 -> 211579.17 | G10: ='Costos Indirectos'!$E$19*Notas!$B$4 -> 72678.571 | H10: ='Hw&SW'!$D$8 -> 18500 | I10: HP Pavilion | J10: ='Hw&SW'!$D$12 -> 18000 | K10: ='Hw&SW'!$D$13 -> 980 | L10: =F10+G10+H10+J10+K10 -> 321737.74 | M10: =L10/Notas!$B$3 -> 17391.229 | N10: =L10/$L$12 -> 0.1374883
A11: 7 | B11: Integrante 7 | C11: =Sueldos!B9 -> Ingeniero DevOps (ambiente, configuración y despliegue) | D11: =Sueldos!G9 -> 5.5 | E11: =Sueldos!C9 -> 16192.283 | F11: =D11*E11 -> 89057.559 | G11: ='Costos Indirectos'!$E$19*Notas!$B$4 -> 72678.571 | H11: ='Hw&SW'!$D$8 -> 18500 | I11: Dell Inspiron | J11: ='Hw&SW'!$D$11 -> 22000 | K11: ='Hw&SW'!$D$13 -> 980 | L11: =F11+G11+H11+J11+K11 -> 203216.13 | M11: =L11/Notas!$B$3 -> 10984.656 | N11: =L11/$L$12 -> 0.086840418
B12: Total | D12: =SUM(D5:D11) -> 48 | F12: =SUM(F5:F11) -> 1536000 | G12: =SUM(G5:G11) -> 508750 | H12: =SUM(H5:H11) -> 129500 | J12: =SUM(J5:J11) -> 159000 | K12: =SUM(K5:K11) -> 6860 | L12: =SUM(L5:L11) -> 2340110 | M12: =SUM(M5:M11) -> 126492.43 | N12: =SUM(N5:N11) -> 1
B14: Comprobación contra las otras hojas
B15: Sueldo total = Sueldos!F18 | C15: =IF(ROUND(F12-Sueldos!F18,2)=0,"Cuadra","Revisar") -> Cuadra
B16: Indirectos = TotalProyecto!C4 | C16: =IF(ROUND(G12-TotalProyecto!C4,2)=0,"Cuadra","Revisar") -> Cuadra
B17: Licencias = 'Hw&SW'!E8 | C17: =IF(ROUND(H12-'Hw&SW'!E8,2)=0,"Cuadra","Revisar") -> Cuadra
B18: Equipo de cómputo = 'Hw&SW'!E10:E12 | C18: =IF(ROUND(J12-SUM('Hw&SW'!E10:E12),2)=0,"Cuadra","Revisar") -> Cuadra
B19: Office 365 = 'Hw&SW'!E13 | C19: =IF(ROUND(K12-'Hw&SW'!E13,2)=0,"Cuadra","Revisar") -> Cuadra
B20: Meses equivalentes = persona-mes de Sueldos | C20: =IF(ROUND(D12-Sueldos!H18,2)=0,"Cuadra","Revisar") -> Cuadra
B22: Notas
B23: Los integrantes se identifican por puesto; los nombres se capturan en la columna B cuando se asigne el personal.
B24: El puesto Desarrollador .NET tiene 2 recursos en la hoja Sueldos, por eso aparece en dos renglones con 6.45 meses cada uno.
B25: Indirectos = costo indirecto por empleado al mes × 15 meses: cada integrante ocupa un lugar en la oficina durante todo el proyecto.
B26: La MacBook Pro se asigna al desarrollador que compila la versión iOS de la aplicación .NET MAUI.

Sheet Otros
B2: Otros Costos
B3: Descripción | C3: Nùmero | D3: Costo (MXN) | E3: Total (MXN) | F3: Costo (USD)
B4: Auditoría de seguridad y pruebas de penetración | C4: 1 | D4: =+F4*Notas!$B$3 -> 370000 | E4: =+D4*C4 -> 370000 | F4: 20000
B5: Gestión del cambio y comunicación interna | C5: 1 | D5: =+F5*Notas!$B$3 -> 185000 | E5: =+D5*C5 -> 185000 | F5: 10000
B10: Totales | E10: =SUM(E4:E9) -> 555000 | F10: =+E10/Notas!$B$3 -> 30000
B12: No se presupuestan viajes: el proyecto se ejecuta en la Ciudad de México y la integración con el corporativo de España es por web service.

Sheet TotalProyecto
B2: Resumen Costos
B3: Descripciòn | C3: Costo (MXN) | D3: Costo (USD) | E3: Origen
B4: Indirectos | C4: =+'Costos Indirectos'!E19*'Hw&SW'!J3*'Hw&SW'!J2 -> 508750 | D4: =+C4/Notas!$B$3 -> 27500 | E4: Costo indirecto por empleado al mes × 7 empleados × 15 meses (fórmula de la plantilla y de la P1)
B5: Infraestructura | C5: =+'Hw&SW'!E16 -> 14969560 | D5: =+C5/Notas!$B$3 -> 809165.41 | E5: Hoja Hw&SW, incluye equipo de cómputo y Office 365 del equipo (Documento 2, sección 3.3)
B6: Sueldos | C6: =+Sueldos!F18 -> 1536000 | D6: =+C6/Notas!$B$3 -> 83027.027 | E6: Hoja Sueldos: 48.0 persona-mes (COCOMO II) × 32,000 MXN
B7: Otros | C7: =+Otros!E10 -> 555000 | D7: =+C7/Notas!$B$3 -> 30000 | E7: Hoja Otros (Documento 2, sección 3.3)
B8: Costos directos del proyecto | C8: =SUM(C4:C7) -> 17569310 | D8: =+C8/Notas!$B$3 -> 949692.43 | E8: Suma de los cuatro rubros anteriores
B9: Reserva de contingencia (10%) | C9: =+C8*0.1 -> 1756931 | D9: =+C9/Notas!$B$3 -> 94969.243 | E9: Documento 2, sección 3.3
B10: Línea base de costos | C10: =+C8+C9 -> 19326241 | D10: =+C10/Notas!$B$3 -> 1044661.7 | E10: Costos directos más la reserva de contingencia
B11: Reserva de gestión | C11: =+C12-C10 -> 17673759 | D11: =+C11/Notas!$B$3 -> 955338.32 | E11: Lo que resta del presupuesto autorizado; queda bajo control del patrocinador
B12: Presupuesto autorizado | C12: =2000000*Notas!$B$3 -> 37000000 | D12: =+C12/Notas!$B$3 -> 2000000 | E12: Enunciado de la Práctica 2: 2 millones de USD
B13: Margen de la línea base contra el presupuesto | C13: =IF(C10<=C12,"Dentro del presupuesto","Excede el presupuesto") -> Dentro del presupuesto | D13: =IF(C10<=C12,"Margen: "&TEXT((C12-C10)/Notas!$B$3,"$#,##0")&" USD","") -> Margen: $955,338 USD | E13: La línea base debe caber en el presupuesto autorizado
B15: Las cifras de este resumen coinciden con el Documento 2, sección 3.3: costos directos, reservas y presupuesto autorizado, incluidos los costos indirectos.
B17: Esfuerzo COCOMO II (persona-mes) | C17: =Sueldos!H18 -> 48
B18: Duración del proyecto (meses) | C18: =Notas!B4 -> 15

Sheet Notas
A1: Costos del proyecto – Academia de idiomas (Equipo 7)
A2: Parámetros del cálculo (celdas que se pueden ajustar)
A3: Tipo de cambio (MXN por USD) | B3: 18.5 | C3: Tipo de cambio de referencia usado en el Documento 2.
A4: Duración del proyecto (meses) | B4: 15 | C4: Documento 1, gráfica de Gantt: Inicio 1.5, Elaboración 4.5, Construcción 7.4 y Transición 1.5 meses (≈ 15 meses).
A5: Equipo máximo del proyecto (personas) | B5: =Sueldos!D18 -> 7 | C5: Personas simultáneas en la hoja Sueldos. El promedio es 48.0 persona-mes / 15 meses = 3.2 personas.
A6: Esfuerzo total (persona-mes) | B6: =Sueldos!H18 -> 48 | C6: COCOMO II de diseño temprano (Documento 1): 40.6 PM en Elaboración y Construcción; 47.9 PM con Inicio y Transición; la distribución por actividad suma 48.0 PM.
A7: Sueldo por hora (MXN) | B7: 200 | C7: Enunciado de la Práctica 2: sueldo promedio de 200 pesos la hora.
A8: Horas por mes | B8: 160 | C8: Base mensual usada en el Documento 2 (160 h/mes).
A10: Notas del Equipo 7
A11: 1. Las cifras del Documento 2 están en dólares; en este libro se convierten a pesos con el tipo de cambio de la celda B3, porque la plantilla y el sueldo de la práctica están en pesos.
A12: 2. Sueldos: la práctica fija un sueldo promedio de 200 pesos por hora. Cada puesto parte del sueldo de la Práctica 1 y se ajusta con un factor común para que el promedio ponderado por persona-mes sea de 32,000 MXN (200 × 160 h); el total de sueldos no cambia.
A13: 3. En la hoja Sueldos, los persona-mes de cada puesto salen de la distribución por actividad RUP/MBASE de COCOMO II (hoja COCOMO_Doc1). Recursos es el número máximo de personas simultáneas y Tiempo a Utilizar son los meses equivalentes de tiempo completo.
A14: 4. Correcciones a las fórmulas de la plantilla: en Hw&SW cada renglón multiplica cantidad por costo y, cuando el gasto es recurrente, por los meses. En TotalProyecto el total suma C4:C7 (incluye Otros).
A15: 5. Los costos indirectos (renta, luz, agua, limpieza, papelería, varios y caja) son valores de referencia de la plantilla. Como en la Práctica 1, se reparten entre los empleados del equipo (7) y se cargan por empleado × meses del proyecto.
A16: 6. La reserva de contingencia (10%) y la reserva de gestión coinciden con el Documento 2, sección 3.3.
A17: 7. La distribución por actividad de COCOMO II suma 48.0 PM y la de fases 47.9 PM (costo de la herramienta: $1,532,357 MXN). El presupuesto usa 48.0 PM: $3,643 MXN más (0.2%), por redondeo del reporte.
A20: Comparación de esfuerzo con la Práctica 1
A21: Horas estimadas por puntos de casos de uso (P1_Costos_Proyecto_UCP_4, UUCP!E50) | B21: 7109.3754
A22: Horas estimadas con COCOMO II (48.0 persona-mes × 160 h) | B22: =Sueldos!H18*Notas!B8 -> 7680
A23: Diferencia COCOMO II contra UCP | B23: =B22/B21-1 -> 0.080263675 | C23: La diferencia es de alrededor de 8%, lo que respalda el esfuerzo de COCOMO II.
A25: Ajuste de sueldos por puesto (Práctica 1 → promedio de 200 MXN/h)
A26: Promedio ponderado de los sueldos base de la P1 (MXN/mes) | B26: =SUMPRODUCT(Sueldos!J4:J9,Sueldos!H4:H9)/Sueldos!H18 -> 29643.75
A27: Factor de ajuste = 32,000 ÷ promedio ponderado | B27: =(Notas!B7*Notas!B8)/B26 -> 1.0794856 | C27: Mismo criterio que el libro P2_Estimacion_Tiempo_Costo_PF. El DevOps toma el sueldo del Implementador de la P1, el puesto de despliegue más parecido.

Sheet COCOMO_Doc1
A1: COCOMO II de diseño temprano – resultados del Documento 1 (P2_JD)
A2: 136 PF sin ajustar, lenguaje de 3ª generación (10,880 SLOC), factores de escala y de costo nominales, EAF = 1.00, 32,000 MXN por persona-mes.
A4: Escenario | B4: Persona-mes | C4: Costo de personal | D4: Indirectos | E4: Línea base | F4: Margen vs. $2 MDD
A5: Inicio | B5: 2.4 | C5: 1.5 | D5: 1.6 | E5: 77916 | F5: =B5*Notas!$B$7*Notas!$B$8 -> 76800
A6: Elaboración | B6: 9.7 | C6: 4.5 | D6: 2.2 | E6: 311666 | F6: =B6*Notas!$B$7*Notas!$B$8 -> 310400
A7: Construcción | B7: 30.8 | C7: 7.4 | D7: 4.1 | E7: 986942 | F7: =B7*Notas!$B$7*Notas!$B$8 -> 985600
A8: Transición | B8: 4.9 | C8: 1.5 | D8: 3.3 | E8: 155833 | F8: =B8*Notas!$B$7*Notas!$B$8 -> 156800
A9: Total | B9: =SUM(B5:B8) -> 47.8 | C9: =SUM(C5:C8) -> 14.9 | E9: =SUM(E5:E8) -> 1532357 | F9: =SUM(F5:F8) -> 1529600
A10: Elaboración + Construcción (lo que reporta COCOMO II como Effort y Schedule) | B10: =B6+B7 -> 40.5 | C10: =C6+C7 -> 11.9 | D10: La herramienta reporta 40.6 PM por redondeo de las fases.
A12: Actividad | B12: Inicio | C12: Elaboración | D12: Construcción | E12: Transición | F12: Total (PM) | G12: Puesto en la hoja Sueldos
A13: Management | B13: 0.3 | C13: 1.2 | D13: 3.1 | E13: 0.7 | F13: =SUM(B13:E13) -> 5.3 | G13: Director de proyecto
A14: Environment/CM | B14: 0.2 | C14: 0.8 | D14: 1.5 | E14: 0.2 | F14: =SUM(B14:E14) -> 2.7 | G14: Ingeniero DevOps
A15: Requirements | B15: 0.9 | C15: 1.8 | D15: 2.5 | E15: 0.2 | F15: =SUM(B15:E15) -> 5.4 | G15: Analista de requisitos
A16: Design | B16: 0.5 | C16: 3.5 | D16: 4.9 | E16: 0.2 | F16: =SUM(B16:E16) -> 9.1 | G16: Arquitecto y diseñador
A17: Implementation | B17: 0.2 | C17: 1.3 | D17: 10.5 | E17: 0.9 | F17: =SUM(B17:E17) -> 12.9 | G17: Desarrolladores .NET (2)
A18: Assessment | B18: 0.2 | C18: 1 | D18: 7.4 | E18: 1.2 | F18: =SUM(B18:E18) -> 9.8 | G18: Ingeniero de pruebas (QA)
A19: Deployment | B19: 0.1 | C19: 0.3 | D19: 0.9 | E19: 1.5 | F19: =SUM(B19:E19) -> 2.8 | G19: Ingeniero DevOps
A20: Total | B20: =SUM(B13:B19) -> 2.4 | C20: =SUM(C13:C19) -> 9.9 | D20: =SUM(D13:D19) -> 30.8 | E20: =SUM(E13:E19) -> 4.9 | F20: =SUM(F13:F19) -> 48 | G20: =IF(ROUND(F20,1)=ROUND(Sueldos!H18,1),"Cuadra con Sueldos","Revisar Sueldos") -> Cuadra con Sueldos
A22: Compresión máxima del calendario (SCED muy bajo = 75%, multiplicador 1.43)
A23: Duración comprimida (meses) | B23: =C9*0.75 -> 11.175
A24: Esfuerzo con compresión (PM) | B24: =Sueldos!H18*1.43 -> 68.64
A25: Aun con la compresión máxima del modelo, la duración queda por encima de los 10 meses del enunciado.

Sheet Sensibilidad
A1: Análisis de sensibilidad (USD) – Documento 2, sección 3.3
A2: Las demás partidas se mantienen constantes, incluidos los indirectos (oficina del equipo durante los 15 meses).
A5: Base: COCOMO II (48.0 PM, $200 MXN/h) | B5: =Sueldos!H18 -> 48 | C5: =B5*Notas!$B$7*Notas!$B$8/Notas!$B$3 -> 83027.027 | D5: =TotalProyecto!$C$4/Notas!$B$3 -> 27500 | E5: =(C5+D5+('Hw&SW'!$E$16+Otros!$E$10)/Notas!$B$3)*1.1 -> 1044661.7 | F5: =2000000-E5 -> 955338.32
A6: Esfuerzo +30% | B6: =Sueldos!H18*1.3 -> 62.4 | C6: =B6*Notas!$B$7*Notas!$B$8/Notas!$B$3 -> 107935.14 | D6: =TotalProyecto!$C$4/Notas!$B$3 -> 27500 | E6: =(C6+D6+('Hw&SW'!$E$16+Otros!$E$10)/Notas!$B$3)*1.1 -> 1072060.6 | F6: =2000000-E6 -> 927939.41
A7: Calendario comprimido al 75% (SCED 1.43) | B7: =Sueldos!H18*1.43 -> 68.64 | C7: =B7*Notas!$B$7*Notas!$B$8/Notas!$B$3 -> 118728.65 | D7: =TotalProyecto!$C$4/Notas!$B$3 -> 27500 | E7: =(C7+D7+('Hw&SW'!$E$16+Otros!$E$10)/Notas!$B$3)*1.1 -> 1083933.5 | F7: =2000000-E7 -> 916066.54
A8: Tarifa de mercado ($35 USD/h) | B8: =Sueldos!H18 -> 48 | C8: =B8*Notas!$B$8*35 -> 268800 | D8: =TotalProyecto!$C$4/Notas!$B$3 -> 27500 | E8: =(C8+D8+('Hw&SW'!$E$16+Otros!$E$10)/Notas!$B$3)*1.1 -> 1249011.9 | F8: =2000000-E8 -> 750988.05
